LICENSE
MANIFEST.in
README.md
setup.py
technicolor.py
technicolor.egg-info/PKG-INFO
technicolor.egg-info/SOURCES.txt
technicolor.egg-info/dependency_links.txt
technicolor.egg-info/entry_points.txt
technicolor.egg-info/top_level.txt