Metadata-Version: 1.0
Name: technicolor
Version: 2016.1.12.1823
Summary: logging in colour
Home-page: https://github.com/wdbm/technicolor
Author: Will Breaden Madden
Author-email: w.bm@cern.ch
License: GPLv3
Platform: UNKNOWN
